[
  {
    "length": 3360,
    "breadth": 510,
    "gt": "",
    "dwt": "",
    "dateBuild": "",
    "shipContainerNum": "",
    "flagName": "新加坡",
    "callSign": "9V7400",
    "mmsi": "563201600",
    "imo": "9935117",
    "shipType": "70",
    "nameEn": "WAN HAI A05",
    "navStatus": 0,
    "updateTime": "2024-03-25 17:48:33",
    "draught": 10100,
    "cog": 27879,
    "hdg": 27800,
    "sog": 9054,
    "dest": "XIAMEN,CN",
    "destStd": "",
    "destcode": "",
    "eta": "03-31 21:00",
    "etaStd": "2024-03-31 21:00:00",
    "lat": 24.336610,
    "lon": 159.457591,
    "polName": "SHEKOU",
    "podName": "LONG BEACH,CA",
    "atd": "01:23 15:44",
    "ata": "02-17 05:36",
    "track":
    [
      {
          "portname_cn": "厦门 嵩屿港区",
          "mmsi": 563201600,
          "portname_en": "Xiamen Songyu",
          "porttimezone": 8,
          "ata": "2024-04-01 07:30:31",
          "status": "已靠泊"
      },
      {
          "atd": "2024-03-11 19:32:28",
          "portname_cn": "曼萨尼约",
          "mmsi": 563201600,
          "portname_en": "MANZANILLO",
          "countrycode": "MX",
          "country_en": "The United Mexican States",
          "stayinport": 75.31,
          "porttimezone": -7,
          "country_cn": "墨西哥",
          "portcode": "MXZLO",
          "ata": "2024-03-08 16:13:57",
          "status": "已离泊"
      },
      {
          "atd": "2024-02-28 08:43:10",
          "portname_cn": "奥克兰",
          "mmsi": 563201600,
          "portname_en": "OAKLAND",
          "countrycode": "US",
          "country_en": "United States",
          "stayinport": 37.94,
          "porttimezone": -8,
          "country_cn": "美国",
          "portcode": "USOAK",
          "ata": "2024-02-26 18:46:50",
          "status": "已离泊"
      },
      {
          "atd": "2024-02-21 22:37:15",
          "portname_cn": "长滩",
          "mmsi": 563201600,
          "portname_en": "LONG BEACH",
          "countrycode": "US",
          "country_en": "United States",
          "stayinport": 97.02,
          "porttimezone": -8,
          "country_cn": "美国",
          "portcode": "USLGB",
          "ata": "2024-02-17 21:36:15",
          "status": "已离泊"
      },
      {
          "atd": "2024-01-30 16:34:33",
          "portname_cn": "宁波 梅山岛港",
          "mmsi": 563201600,
          "portname_en": "Ningbo meishandao",
          "countrycode": "CN",
          "country_en": "China",
          "stayinport": 21.76,
          "porttimezone": 8,
          "country_cn": "中国",
          "portcode": "CNMSN",
          "ata": "2024-01-29 18:48:45",
          "status": "已离泊"
      },
      {
          "atd": "2024-01-28 11:44:00",
          "portname_cn": "上海 洋山深水港",
          "mmsi": 563201600,
          "portname_en": "Shanghai Yangshan",
          "countrycode": "CN",
          "country_en": "China",
          "stayinport": 16.41,
          "porttimezone": 8,
          "country_cn": "中国",
          "portcode": "CNYSN",
          "ata": "2024-01-27 19:19:22",
          "status": "已离泊"
      },
      {
          "atd": "2024-01-26 16:00:51",
          "portname_cn": "台北港",
          "mmsi": 563201600,
          "portname_en": "TAIBEI",
          "countrycode": "CN",
          "country_en": "China",
          "stayinport": 19.19,
          "porttimezone": 8,
          "country_cn": "中国",
          "portcode": "TWTPE",
          "ata": "2024-01-25 20:49:37",
          "status": "已离泊"
      },
      {
          "atd": "2024-01-25 07:04:59",
          "portname_cn": "厦门 海沧港区",
          "mmsi": 563201600,
          "portname_en": "Xiamen Haicang",
          "countrycode": "CN",
          "country_en": "China",
          "stayinport": 17.09,
          "porttimezone": 8,
          "country_cn": "中国",
          "portcode": "CNXMH",
          "ata": "2024-01-24 13:59:50",
          "status": "已离泊"
      },
      {
          "atd": "2024-01-23 15:44:03",
          "portname_cn": "深圳 蛇口港",
          "mmsi": 563201600,
          "portname_en": "Shenzhen SheKou",
          "countrycode": "CN",
          "country_en": "China",
          "stayinport": 45.73,
          "porttimezone": 8,
          "country_cn": "中国",
          "portcode": "CNSHK",
          "ata": "2024-01-21 18:00:07",
          "status": "已离泊"
      },
      {
          "atd": "2024-01-19 10:38:25",
          "portname_cn": "盖梅港",
          "mmsi": 563201600,
          "portname_en": "Cai Mep",
          "countrycode": "VN",
          "country_en": "Vietnam",
          "stayinport": 27.19,
          "porttimezone": 7,
          "country_cn": "越南",
          "portcode": "VNCMT",
          "ata": "2024-01-18 07:26:48",
          "status": "已离泊"
      },
      {
          "atd": "2023-12-13 22:10:03",
          "portname_cn": "萨凡纳",
          "mmsi": 563201600,
          "portname_en": "SAVANNAH",
          "countrycode": "US",
          "country_en": "United States",
          "stayinport": 37.92,
          "porttimezone": -5,
          "country_cn": "美国",
          "portcode": "USSAV",
          "ata": "2023-12-12 08:15:03",
          "status": "已离泊"
      },
      {
          "atd": "2023-12-10 10:17:46",
          "portname_cn": "查尔斯顿",
          "mmsi": 563201600,
          "portname_en": "CHARLESTON",
          "countrycode": "US",
          "country_en": "United States",
          "stayinport": 30.53,
          "porttimezone": -5,
          "country_cn": "美国",
          "portcode": "USCHS",
          "ata": "2023-12-09 03:45:46",
          "status": "已离泊"
      },
      {
          "atd": "2023-12-07 07:40:02",
          "portname_cn": "诺福克",
          "mmsi": 563201600,
          "portname_en": "NORFOLK VA",
          "countrycode": "US",
          "country_en": "United States",
          "stayinport": 24.58,
          "porttimezone": -5,
          "country_cn": "美国",
          "portcode": "USORF",
          "ata": "2023-12-06 07:05:03",
          "status": "已离泊"
      },
      {
          "atd": "2023-12-03 11:55:08",
          "portname_cn": "",
          "mmsi": 563201600,
          "portname_en": "NEW YORK & NEW JERSEY",
          "countrycode": "US",
          "country_en": "United States",
          "stayinport": 47.17,
          "porttimezone": -5,
          "country_cn": "美国",
          "portcode": "",
          "ata": "2023-12-01 12:45:03",
          "status": "已离泊"
      },
      {
          "atd": "2023-11-07 21:35:39",
          "portname_cn": "科伦坡",
          "mmsi": 563201600,
          "portname_en": "COLOMBO",
          "countrycode": "LK",
          "country_en": "Sri Lanka",
          "stayinport": 15.69,
          "porttimezone": 5,
          "country_cn": "斯里兰卡",
          "portcode": "LKCMB",
          "ata": "2023-11-07 05:54:22",
          "status": "已离泊"
      },
      {
          "atd": "2023-11-03 15:23:54",
          "portname_cn": "裕廊港",
          "mmsi": 563201600,
          "portname_en": "JURONG ISLAND",
          "countrycode": "SG",
          "country_en": "Singapore",
          "stayinport": 25.11,
          "porttimezone": 7,
          "country_cn": "新加坡",
          "portcode": "SGJUR",
          "ata": "2023-11-02 14:17:13",
          "status": "已离泊"
      },
      {
          "atd": "2023-10-31 11:37:16",
          "portname_cn": "盖梅港",
          "mmsi": 563201600,
          "portname_en": "Cai Mep",
          "countrycode": "VN",
          "country_en": "Vietnam",
          "stayinport": 25.37,
          "porttimezone": 7,
          "country_cn": "越南",
          "portcode": "VNCMT",
          "ata": "2023-10-30 10:15:06",
          "status": "已离泊"
      },
      {
          "atd": "2023-10-26 22:00:14",
          "portname_cn": "深圳 蛇口港",
          "mmsi": 563201600,
          "portname_en": "Shenzhen SheKou",
          "countrycode": "CN",
          "country_en": "China",
          "stayinport": 20.58,
          "porttimezone": 8,
          "country_cn": "中国",
          "portcode": "CNSHK",
          "ata": "2023-10-26 01:25:16",
          "status": "已离泊"
      },
      {
          "atd": "2023-10-24 20:56:39",
          "portname_cn": "台北港",
          "mmsi": 563201600,
          "portname_en": "TAIBEI",
          "countrycode": "CN",
          "country_en": "China",
          "stayinport": 14.49,
          "porttimezone": 8,
          "country_cn": "中国",
          "portcode": "TWTPE",
          "ata": "2023-10-24 06:27:27",
          "status": "已离泊"
      },
      {
          "atd": "2023-10-23 01:13:49",
          "portname_cn": "宁波 北仑港",
          "mmsi": 563201600,
          "portname_en": "Ningbo BEILUN",
          "countrycode": "CN",
          "country_en": "China",
          "stayinport": 15.55,
          "porttimezone": 8,
          "country_cn": "中国",
          "portcode": "CNBEI",
          "ata": "2023-10-22 09:40:58",
          "status": "已离泊"
      },
      {
          "atd": "2023-10-19 04:12:38",
          "portname_cn": "上海 洋山深水港",
          "mmsi": 563201600,
          "portname_en": "Shanghai Yangshan",
          "countrycode": "CN",
          "country_en": "China",
          "stayinport": 15.26,
          "porttimezone": 8,
          "country_cn": "中国",
          "portcode": "CNYSN",
          "ata": "2023-10-18 12:56:55",
          "status": "已离泊"
      }
  ]
  },
  {
    "length": 260,
    "breadth": 120,
    "gt": "",
    "dwt": "",
    "dateBuild": "",
    "shipContainerNum": "",
    "flagName": "加拿大",
    "callSign": "CFN6644",
    "mmsi": "316020868",
    "imo": "9623128",
    "shipType": "52",
    "nameEn": "SEASPAN OSPREY",
    "navStatus": 5,
    "updateTime": "2024-03-25 17:52:52",
    "draught": 5400,
    "cog": 9240,
    "hdg": 29800,
    "sog": 0,
    "dest": "VANCOUVER,US",
    "destStd": "",
    "destcode": "",
    "eta": "11-24 13:00",
    "etaStd": "2023-11-24 13:00:00",
    "lat": 49.014930,
    "lon": -123.155138
  },
  {
    "length": 1720,
    "breadth": 280,
    "gt": "",
    "dwt": "",
    "dateBuild": "2022-01-01 00:00:00",
    "shipContainerNum": "",
    "flagName": "利比里亚",
    "callSign": "5LFU8",
    "mmsi": "636021814",
    "imo": "9555175",
    "shipType": "70",
    "nameEn": "WAN HAI 178",
    "navStatus": 1,
    "updateTime": "2024-03-25 17:54:32",
    "draught": 10000,
    "cog": 33850,
    "hdg": 33800,
    "sog": 7510,
    "dest": "KAOHSIUNG,CN",
    "destStd": "",
    "destcode": "",
    "eta": "03-25 08:00",
    "etaStd": "2024-03-25 08:00:00",
    "lat": 22.515550,
    "lon": 113.741113
  },
  {
    "length": 3660,
    "breadth": 510,
    "gt": "",
    "dwt": "",
    "dateBuild": "",
    "shipContainerNum": "",
    "flagName": "利比里亚",
    "callSign": "5LMW3",
    "mmsi": "636023269",
    "imo": "9946879",
    "shipType": "70",
    "nameEn": "MSCCARMELITA",
    "navStatus": 3,
    "updateTime": "2024-03-25 17:56:55",
    "draught": 11400,
    "cog": 23800,
    "hdg": "",
    "sog": 9774,
    "dest": "BUSAN,KR",
    "destStd": "",
    "destcode": "",
    "eta": "03-29 12:00",
    "etaStd": "2024-03-29 12:00:00",
    "lat": 50.483333,
    "lon": 162.281666
  },
  {
    "length": 3660,
    "breadth": 520,
    "gt": "",
    "dwt": "",
    "dateBuild": "2018-01-01 00:00:00",
    "shipContainerNum": "",
    "flagName": "中国香港",
    "callSign": "VRRT3",
    "mmsi": "477166600",
    "imo": "9757876",
    "shipType": "71",
    "nameEn": "COSCOSHIPPING DENALI",
    "navStatus": 5,
    "updateTime": "2024-03-25 17:58:15",
    "draught": 12900,
    "cog": 29140,
    "hdg": 100,
    "sog": 0,
    "dest": "KAOHSIUNG,CN",
    "destStd": "",
    "destcode": "",
    "eta": "03-23 12:00",
    "etaStd": "2024-03-23 12:00:00",
    "lat": 33.760375,
    "lon": -118.214211
  },
  {
    "length": 3660,
    "breadth": 520,
    "gt": "",
    "dwt": "",
    "dateBuild": "2018-01-01 00:00:00",
    "shipContainerNum": "",
    "flagName": "中国香港",
    "callSign": "VRRJ2",
    "mmsi": "477148700",
    "imo": "9757864",
    "shipType": "70",
    "nameEn": "COSCO SHIPPING ALPS",
    "navStatus": 0,
    "updateTime": "2024-03-25 13:35:44",
    "draught": 13000,
    "cog": 26500,
    "hdg": "",
    "sog": 6687,
    "dest": "KAOHSIUNG,CN",
    "destStd": "",
    "destcode": "",
    "eta": "20-24 -0:3-29 12:00:00",
    "etaStd": "",
    "lat": 23.436666,
    "lon": 142.813333
  },
  {
    "length": 3670,
    "breadth": 430,
    "gt": "",
    "dwt": "",
    "dateBuild": "2008-01-01 00:00:00",
    "shipContainerNum": "",
    "flagName": "中国香港",
    "callSign": "VRVO3",
    "mmsi": "477891200",
    "imo": "9359002",
    "shipType": "71",
    "nameEn": "GERNERMAERSK",
    "navStatus": 0,
    "updateTime": "2024-03-25 18:00:30",
    "draught": 11000,
    "cog": 32300,
    "hdg": "",
    "sog": 8231,
    "dest": "USOAKCNQDG",
    "destStd": "",
    "destcode": "",
    "eta": "03-27 03:00",
    "etaStd": "2024-03-27 03:00:00",
    "lat": 30.211666,
    "lon": 128.848333
  }
]
